{
  "posts":[
    {
      "title": "Week 1 - Back to Work",
      "date": "2018-01-20",
      "file": "2018-01-20-week-1.md",
      "type": "0"
    } ,

    {
      "title": "Week 2 - Getting Settled",
      "date": "2018-01-26",
      "file": "2018-1-26-week-2.md",
      "type": "0"
    } ,

    {
      "title": "Week 3 - More of the Same",
      "date": "2018-02-02",
      "file": "2018-02-02-week-3.md",
      "type": "0"
    } ,

    {
      "title": "Week 4 - Ramping Up",
      "date": "2018-02-09",
      "file": "2018-02-09-week-4.md",
      "type": "0"
    } ,

    {
      "title": "Week 5 - Trial by Fire",
      "date": "2018-02-17",
      "file": "2018-02-17-week-5.md",
      "type": "0"
    } ,

    {
      "title": "Week 6 - The Usual",
      "date": "2018-02-24",
      "file": "2018-02-24-week-6.md",
      "type": "0"
    } ,
    {
      "title": "Week 7 - Exam Week",
      "date": "2018-03-03",
      "file": "2018-03-03-week-7.md",
      "type": "0"
    } ,

    {
      "title": "Week 8 - Spring Break",
      "date": "2018-03-10",
      "file": "2018-03-10-week-8.md",
      "type": "0"
    } ,

    {
      "title": "Week 9 - Crunch Time",
      "date": "2018-03-24",
      "file": "2018-03-24-week-9.md",
      "type": "0"
    } ,

    {
      "title": "Week 10 - Cruising Along",
      "date": "2018-03-31",
      "file": "2018-03-31-week-10.md",
      "type": "0"
    } ,

    {
      "title": "Week 11 - Work Work Work",
      "date": "2018-04-06",
      "file": "2018-04-06-week-11.md",
      "type": "0"
    } ,

    {
      "title": "Week 12 - More of the Same",
      "date": "2018-04-14",
      "file": "2018-04-14-week-12.md",
      "type": "0"
    } ,

    {
      "title": "Closing Thoughts: Final Entry",
      "date": "2018-05-04",
      "file": "2018-05-04-final-post.md",
      "type": "0"
    },

    {
      "title": "Remodeling",
      "date": "2018-05-13",
      "file": "2018-05-13-summer-1.md",
      "type": "1"
    },

    {
      "title": "Week of Relaxation",
      "date": "2018-05-19",
      "file": "2018-05-19-summer-2.md",
      "type": "1"
    },

    {
      "title": "First Week of Work",
      "date": "2018-05-26",
      "file": "2018-05-26-summer-3.md",
      "type": "1"
    } ,

    {
      "title": "A Trip Downtown",
      "date": "2018-06-03",
      "file": "2018-06-03-summer-4.md",
      "type": "1"
    } ,

    {
      "title": "A Nondescript Week",
      "date": "2018-06-11",
      "file": "2018-06-11-summer-5.md",
      "type": "1"
    } ,

    {
      "title": "Corgis!",
      "date": "2018-06-11",
      "file": "2018-06-17-summer-6.md",
      "type": "1"
    } ,

    {
      "title": "A Momentary Lapse",
      "date": "2018-07-05",
      "file": "2018-07-05-summer-7.md",
      "type": "1"
    } ,
    {
      "title": "A Very Long Lapse",
      "date": "2018-09-05",
      "file": "2018-09-05-fall-1.md",
      "type": "2"
    } ,
    {
      "title": "Long Lapse 2: Electric Boogaloo",
      "date": "2018-11-01",
      "file": "2018-11-01-fall-2.md",
      "type": "2"
    } ,
    {
      "title": "Deadlines Looming",
      "date": "2018-11-11",
      "file": "2018-11-11-fall-3.md",
      "type": "2"
    } ,
    {
      "title": "A Suboptimal Break",
      "date": "2018-11-25",
      "file": "2018-11-25-fall-4.md",
      "type": "2"
    } ,
    {
      "title": "Wrapping Up",
      "date": "2018-11-26",
      "file": "2018-11-26-fall-5.md",
      "type": "2"
    } ,
    {
      "title": "The Home Stretch",
      "date": "2018-12-9",
      "file": "2018-12-9-fall-6.md",
      "type": "2"
    } ,
    {
      "title": "One More Left",
      "date": "2018-12-16",
      "file": "2018-12-16-fall-7.md",
      "type": "2"
    } ,
    {
      "title": "Atom for LaTeX",
      "date": "2018-12-20",
      "file": "2018-12-20-fall-8.md",
      "type": "2"
    } ,
    {
      "title": "Happy New Year!",
      "date": "2019-01-01",
      "file": "2019-01-01-spring-1.md",
      "type": "3"
    } ,
    {
      "title": "Small Update",
      "date": "2019-01-09",
      "file": "2019-01-09-spring-2.md",
      "type": "3"
    } ,
    {
      "title": "Happy Birthday Dan!",
      "date": "2019-01-21",
      "file": "2019-01-21-spring-3.md",
      "type": "3"
    } ,
    {
      "title": "The Last First Week",
      "date": "2019-01-27",
      "file": "2019-01-27-spring-4.md",
      "type": "3"
    } ,
    {
      "title": "Getting in the Groove",
      "date": "2019-02-05",
      "file": "2019-02-05-spring-5.md",
      "type": "3"
    } ,
    {
      "title": "Some Interesting Problems",
      "date": "2019-02-17",
      "file": "2019-02-17-spring-6.md",
      "type": "3"
    } ,
    {
      "title": "More Things I've Learned",
      "date": "2019-02-26",
      "file": "2019-02-26-spring-7.md",
      "type": "3"
    } ,
    {
      "title": "Graduation",
      "date": "2019-05-28",
      "file": "2019-05-28-spring-8.md",
      "type": "3"
    }
  ]
}
